[
    {
        "x": "1175",
        "y": "2550",
        "layerId": "248de15c-07ce-4746-9279-384186ffe2bf",
        "filename": "SHFH-2F-A-"
    },
    {
        "x": "1090",
        "y": "2773",
        "layerId": "248de15c-07ce-4746-9279-384186ffe2bf",
        "filename": "SHFH-2F-B-"
    },
    {
        "x": "952",
        "y": "2773",
        "layerId": "248de15c-07ce-4746-9279-384186ffe2bf",
        "filename": "SHFH-2F-C-"
    },
    {
        "x": "916",
        "y": "2688",
        "layerId": "248de15c-07ce-4746-9279-384186ffe2bf",
        "filename": "SHFH-2F-D-"
    },
    {
        "x": "843",
        "y": "2684",
        "layerId": "248de15c-07ce-4746-9279-384186ffe2bf",
        "filename": "SHFH-2F-E-"
    },
    {
        "x": "837",
        "y": "2688",
        "layerId": "6b15eb9c-0453-4b01-aff1-54f2ed994f41",
        "filename": "SHFH-3F-A-"
    },
    {
        "x": "912",
        "y": "2688",
        "layerId": "6b15eb9c-0453-4b01-aff1-54f2ed994f41",
        "filename": "SHFH-3F-B-"
    },
    {
        "x": "952",
        "y": "2776",
        "layerId": "6b15eb9c-0453-4b01-aff1-54f2ed994f41",
        "filename": "SHFH-3F-C-"
    },
    {
        "x": "1099",
        "y": "2776",
        "layerId": "6b15eb9c-0453-4b01-aff1-54f2ed994f41",
        "filename": "SHFH-3F-D-"
    },
    {
        "x": "1395",
        "y": "2776",
        "layerId": "6b15eb9c-0453-4b01-aff1-54f2ed994f41",
        "filename": "SHFH-3F-E-"
    },
    {
        "x": "1552",
        "y": "2773",
        "layerId": "6b15eb9c-0453-4b01-aff1-54f2ed994f41",
        "filename": "SHFH-3F-F-"
    },
    {
        "x": "1556",
        "y": "2419",
        "layerId": "6b15eb9c-0453-4b01-aff1-54f2ed994f41",
        "filename": "SHFH-3F-G-"
    },
    {
        "x": "1559",
        "y": "2051",
        "layerId": "6b15eb9c-0453-4b01-aff1-54f2ed994f41",
        "filename": "SHFH-3F-H-"
    },
    {
        "x": "1897",
        "y": "2045",
        "layerId": "6b15eb9c-0453-4b01-aff1-54f2ed994f41",
        "filename": "SHFH-3F-I-"
    },
    {
        "x": "1903",
        "y": "1897",
        "layerId": "6b15eb9c-0453-4b01-aff1-54f2ed994f41",
        "filename": "SHFH-3F-J-"
    },
    {
        "x": "1900",
        "y": "1329",
        "layerId": "6b15eb9c-0453-4b01-aff1-54f2ed994f41",
        "filename": "SHFH-3F-K-"
    },
    {
        "x": "1903",
        "y": "1244",
        "layerId": "6b15eb9c-0453-4b01-aff1-54f2ed994f41",
        "filename": "SHFH-3F-L-"
    },
    {
        "x": "2186",
        "y": "1237",
        "layerId": "6b15eb9c-0453-4b01-aff1-54f2ed994f41",
        "filename": "SHFH-3F-M-"
    },
    {
        "x": "2451",
        "y": "1237",
        "layerId": "6b15eb9c-0453-4b01-aff1-54f2ed994f41",
        "filename": "SHFH-3F-N-"
    },
    {
        "x": "2524",
        "y": "1162",
        "layerId": "6b15eb9c-0453-4b01-aff1-54f2ed994f41",
        "filename": "SHFH-3F-O-"
    },
    {
        "x": "2458",
        "y": "1090",
        "layerId": "6b15eb9c-0453-4b01-aff1-54f2ed994f41",
        "filename": "SHFH-3F-P-"
    },
    {
        "x": "2258",
        "y": "893",
        "layerId": "6b15eb9c-0453-4b01-aff1-54f2ed994f41",
        "filename": "SHFH-3F-Q-"
    },
    {
        "x": "2041",
        "y": "683",
        "layerId": "6b15eb9c-0453-4b01-aff1-54f2ed994f41",
        "filename": "SHFH-3F-R-"
    },
    {
        "x": "1802",
        "y": "453",
        "layerId": "6b15eb9c-0453-4b01-aff1-54f2ed994f41",
        "filename": "SHFH-3F-S-"
    },
    {
        "x": "1733",
        "y": "473",
        "layerId": "6b15eb9c-0453-4b01-aff1-54f2ed994f41",
        "filename": "SHFH-3F-T-"
    },
    {
        "x": "1690",
        "y": "430",
        "layerId": "6b15eb9c-0453-4b01-aff1-54f2ed994f41",
        "filename": "SHFH-3F-U-"
    },
    {
        "x": "1674",
        "y": "456",
        "layerId": "b125a62d-2efb-4c3f-83cb-8b0bc718c2d3",
        "filename": "SHFH-13F-A-"
    },
    {
        "x": "1641",
        "y": "541",
        "layerId": "b125a62d-2efb-4c3f-83cb-8b0bc718c2d3",
        "filename": "SHFH-13F-B-"
    },
    {
        "x": "1601",
        "y": "591",
        "layerId": "b125a62d-2efb-4c3f-83cb-8b0bc718c2d3",
        "filename": "SHFH-13F-C-"
    },
    {
        "x": "1552",
        "y": "640",
        "layerId": "b125a62d-2efb-4c3f-83cb-8b0bc718c2d3",
        "filename": "SHFH-13F-D-"
    },
    {
        "x": "1470",
        "y": "683",
        "layerId": "b125a62d-2efb-4c3f-83cb-8b0bc718c2d3",
        "filename": "SHFH-13F-E-"
    },
    {
        "x": "1667",
        "y": "870",
        "layerId": "b125a62d-2efb-4c3f-83cb-8b0bc718c2d3",
        "filename": "SHFH-13F-F-"
    },
    {
        "x": "1510",
        "y": "601",
        "layerId": "b125a62d-2efb-4c3f-83cb-8b0bc718c2d3",
        "filename": "SHFH-13F-G-"
    },
    {
        "x": "1559",
        "y": "551",
        "layerId": "b125a62d-2efb-4c3f-83cb-8b0bc718c2d3",
        "filename": "SHFH-13F-H-"
    },
    {
        "x": "1611",
        "y": "505",
        "layerId": "b125a62d-2efb-4c3f-83cb-8b0bc718c2d3",
        "filename": "SHFH-13F-I-"
    },
    {
        "x": "1674",
        "y": "456",
        "layerId": "0be78019-21a3-4e47-810d-c5f34c2823d6",
        "filename": "SHFH-14F-A-"
    },
    {
        "x": "1641",
        "y": "541",
        "layerId": "0be78019-21a3-4e47-810d-c5f34c2823d6",
        "filename": "SHFH-14F-B-"
    },
    {
        "x": "1601",
        "y": "591",
        "layerId": "0be78019-21a3-4e47-810d-c5f34c2823d6",
        "filename": "SHFH-14F-C-"
    },
    {
        "x": "1552",
        "y": "640",
        "layerId": "0be78019-21a3-4e47-810d-c5f34c2823d6",
        "filename": "SHFH-14F-D-"
    },
    {
        "x": "1470",
        "y": "683",
        "layerId": "0be78019-21a3-4e47-810d-c5f34c2823d6",
        "filename": "SHFH-14F-E-"
    },
    {
        "x": "1667",
        "y": "870",
        "layerId": "0be78019-21a3-4e47-810d-c5f34c2823d6",
        "filename": "SHFH-14F-F-"
    },
    {
        "x": "1510",
        "y": "601",
        "layerId": "0be78019-21a3-4e47-810d-c5f34c2823d6",
        "filename": "SHFH-14F-G-"
    },
    {
        "x": "1559",
        "y": "551",
        "layerId": "0be78019-21a3-4e47-810d-c5f34c2823d6",
        "filename": "SHFH-14F-H-"
    },
    {
        "x": "1611",
        "y": "505",
        "layerId": "0be78019-21a3-4e47-810d-c5f34c2823d6",
        "filename": "SHFH-14F-I-"
    }
]